{
  "resolution_no": "1295",
  "year": "2000",
  "theme": [
    "Sanctions",
    "Peacekeeping",
    "Conflict Resolution"
  ],
  "chapter": "Chapter VII",
  "charter_articles": [
    "Article 41",
    "Article 24",
    "Article 25"
  ],
  "entities": [
    "UNITA",
    "OAU",
    "SADC",
    "Interpol"
  ],
  "reporting_cycle": "The Secretary-General reports periodically to the Committee",
  "operative_authority": "Chapter VII",
  "summary": "**Other**\n\n* Welcomes the OAU's appeal to its member states to work for the implementation of sanctions.\n* Underlines SADC's important role in implementing sanctions and invites SADC to identify its assistance needs.\nThe Security Council:\nundertakes to convey the report of the Panel of Experts to the Chairman of SADC, and requests the Secretary-General to transmit the report to the Executive Secretary of SADC;\nDecides to remain actively seized of the matter.",
  "url": "https://storage.googleapis.com/bluelines-rag-bucket/2000/S_RES_1295_2000_EN.pdf"
}