{
  "resolution_no": "2479",
  "year": "2019",
  "theme": [
    "Peacekeeping",
    "Sudan"
  ],
  "chapter": "Chapter VII",
  "charter_articles": [
    "Article 39"
  ],
  "entities": [
    "UNAMID",
    "African Union Commission",
    "United Nations"
  ],
  "reporting_cycle": "Secretary-General reports every 60 days, Special Report by 30 September 2019",
  "operative_authority": "Chapter VII",
  "summary": "The Security Council, reaffirming previous resolutions and statements on Sudan, and underlining the importance of full compliance with and implementation of these, \nreaffirms its strong commitment to Sudan's sovereignty, unity, independence, and territorial integrity. \nNoting the Special Report of the African Union Commission Chairperson and the UN Secretary-General (S/2019/445), \ndetermines the situation in Sudan threatens international peace and security. \nActing under Chapter VII, \n1. Extends UNAMID's mandate until 31 October 2019; \n2. Decides UNAMID will continue implementing its mandate as set out in resolution 2429 (2018) and temporarily extends the drawdown period for military personnel to maintain self-protection capacities; \n3. Requests the Secretary-General to provide an oral update within 60 days and a Special Report by 30 September 2019, with the African Union Commission Chairperson, on: \n    (i) the situation on the ground and recommendations on UNAMID's drawdown; \n    (ii) a joint African Union-United Nations political strategy for a follow-on mechanism to UNAMID; \n4. Decides to remain seized of the matter.",
  "url": "https://storage.googleapis.com/bluelines-rag-bucket/2019/S_RES_2479_2019_EN.pdf"
}