{
  "resolution_no": "1548",
  "year": "2004",
  "theme": [
    "Peacekeeping"
  ],
  "chapter": "Chapter VI",
  "charter_articles": [],
  "entities": [
    "UNFICYP"
  ],
  "reporting_cycle": "",
  "operative_authority": "Chapter VI",
  "summary": "The Security Council,\nWelcoming the report of the Secretary-General on the United Nations operation in Cyprus, \nReaffirms all its relevant resolutions on Cyprus, in particular resolution 1251 (1999) and subsequent resolutions;\nDecides to extend the mandate of UNFICYP until 15 December 2004;\n Urges the Turkish Cypriot side and Turkish forces to lift all remaining restrictions on UNFICYP and restore the military status quo in Strovilia as of 30 June 2000;\n Requests the Secretary-General to report on the implementation of this resolution; \nDecides to remain seized of the matter; \n Welcoming the Secretary-General's intention to review UNFICYP's mandate, force levels and concept of operation within three months.",
  "url": "https://storage.googleapis.com/bluelines-rag-bucket/2004/S_RES_1548_2004_EN.pdf"
}