{
  "resolution_no": "1631",
  "year": "2005",
  "theme": [
    "Peacekeeping",
    "Regional Organizations",
    "International Cooperation"
  ],
  "chapter": "Chapter VIII",
  "charter_articles": [
    "Article 54",
    "Chapter VIII"
  ],
  "entities": [
    "United Nations",
    "Regional Organizations",
    "African regional and subregional organizations",
    "European Union"
  ],
  "reporting_cycle": "",
  "operative_authority": "Chapter VI",
  "summary": "11. Requests the Secretary-General to include assessments of UN-regional organization cooperation progress in his regular reporting to the Security Council on peacekeeping and peacebuilding operations.\n\n12. Decides to remain seized of the matter.",
  "url": "https://storage.googleapis.com/bluelines-rag-bucket/2005/S_RES_1631_2005_EN.pdf"
}